pivotal/__init__.py
pivotal/api.py
pivotal/errors.py
pivotal/expressions.py
pivotal/simplex.py
pivotal_solver-0.2.0.dist-info/METADATA
pivotal_solver-0.2.0.dist-info/WHEEL
pivotal_solver-0.2.0.dist-info/licenses/LICENSE
pivotal_solver-0.2.0.dist-info/RECORD
