Metadata-Version: 2.4
Name: pivotal-solver
Version: 0.2.0
Summary: High-level Linear Programming solver using the Simplex algorithm
Project-URL: Homepage, https://github.com/tomasr8/pivotal
Project-URL: GitHub, https://github.com/tomasr8/pivotal
Author-email: Tomas Roun <tomas.roun8@gmail.com>
License: Copyright (c) Tomas Roun
License-File: LICENSE
Keywords: convex optimization,linear programming,linear programming solver,linprog,lp,lp solver,numerical optimization,simplex,simplex algorithm,solver
Classifier: Operating System :: OS Independent
Classifier: Programming Language :: Python :: 3
Classifier: Programming Language :: Python :: 3.11
Classifier: Programming Language :: Python :: 3.12
Classifier: Programming Language :: Python :: 3.13
Classifier: Programming Language :: Python :: 3.14
Classifier: Topic :: Scientific/Engineering
Classifier: Topic :: Software Development :: Libraries
Requires-Python: >=3.11
Requires-Dist: numpy~=2.3.5
